pyowl2/__init__.py
pyowl2/abstracts/__init__.py
pyowl2/abstracts/annotation_axiom.py
pyowl2/abstracts/annotation_subject.py
pyowl2/abstracts/annotation_value.py
pyowl2/abstracts/assertion.py
pyowl2/abstracts/axiom.py
pyowl2/abstracts/class_axiom.py
pyowl2/abstracts/class_expression.py
pyowl2/abstracts/data_property_axiom.py
pyowl2/abstracts/data_property_expression.py
pyowl2/abstracts/data_range.py
pyowl2/abstracts/entity.py
pyowl2/abstracts/individual.py
pyowl2/abstracts/object.py
pyowl2/abstracts/object_property_axiom.py
pyowl2/abstracts/object_property_expression.py
pyowl2/abstracts/property_range.py
pyowl2/axioms/__init__.py
pyowl2/axioms/annotations/__init__.py
pyowl2/axioms/annotations/annotation_assertion.py
pyowl2/axioms/annotations/annotation_property_domain.py
pyowl2/axioms/annotations/annotation_property_range.py
pyowl2/axioms/annotations/sub_annotation_property_of.py
pyowl2/axioms/assertion/__init__.py
pyowl2/axioms/assertion/class_assertion.py
pyowl2/axioms/assertion/data_property_assertion.py
pyowl2/axioms/assertion/different_individuals.py
pyowl2/axioms/assertion/negative_data_property_assertion.py
pyowl2/axioms/assertion/negative_object_property_assertion.py
pyowl2/axioms/assertion/object_property_assertion.py
pyowl2/axioms/assertion/same_individual.py
pyowl2/axioms/class_axiom/__init__.py
pyowl2/axioms/class_axiom/disjoint_classes.py
pyowl2/axioms/class_axiom/disjoint_union.py
pyowl2/axioms/class_axiom/equivalent_classes.py
pyowl2/axioms/class_axiom/sub_class_of.py
pyowl2/axioms/data_property_axiom/__init__.py
pyowl2/axioms/data_property_axiom/data_property_domain.py
pyowl2/axioms/data_property_axiom/data_property_range.py
pyowl2/axioms/data_property_axiom/disjoint_data_properties.py
pyowl2/axioms/data_property_axiom/equivalent_data_properties.py
pyowl2/axioms/data_property_axiom/functional_data_property.py
pyowl2/axioms/data_property_axiom/sub_data_property_of.py
pyowl2/axioms/datatype_definition.py
pyowl2/axioms/declaration.py
pyowl2-1.0.3.dist-info/LICENSE
pyowl2-1.0.3.dist-info/METADATA
pyowl2-1.0.3.dist-info/WHEEL
pyowl2-1.0.3.dist-info/RECORD
