Metadata-Version: 2.3
Name: pyowl2
Version: 1.0.3
Summary: A python implementation of the OWL 2 standard. See https://www.w3.org/TR/owl2-syntax/ and https://www.w3.org/TR/owl2-mapping-to-rdf/
License: CC-BY-SA-4.0
Author: Giuseppe Filippone
Author-email: filipponegiuseppe94@gmail.com
Requires-Python: >=3.11,<4.0
Classifier: License :: Other/Proprietary License
Classifier: Programming Language :: Python :: 3
Classifier: Programming Language :: Python :: 3.11
Classifier: Programming Language :: Python :: 3.12
Classifier: Programming Language :: Python :: 3.13
Requires-Dist: owlready2 (>=0.47,<0.48)
Requires-Dist: rdflib (>=7.1.4,<8.0.0)
Requires-Dist: tabulate (>=0.9.0,<0.10.0)
Project-URL: Documentation, https://pyowl2.readthedocs.io/en/latest/
Project-URL: Repository, https://github.com/giuseppefilippone/pyowl2
Project-URL: Source, https://github.com/giuseppefilippone/pyowl2
